bin/__init__.py
bin/analyze.py
bin/bench.py
bin/config.py
bin/drop_databases.py
bin/run.py
bin/test_read_db.py
aiutare_finnbarroc-0.0.1.dist-info/LICENSE
aiutare_finnbarroc-0.0.1.dist-info/METADATA
aiutare_finnbarroc-0.0.1.dist-info/WHEEL
aiutare_finnbarroc-0.0.1.dist-info/top_level.txt
aiutare_finnbarroc-0.0.1.dist-info/RECORD
