Metadata-Version: 2.1
Name: aiutare-finnbarroc
Version: 0.0.1
Summary: A benchmarking framework for SAT, SMT, and equivalence checking programs.
Home-page: https://github.com/FedericoAureliano/aiutare
Author: Federico Mora, Lukas Finnbarr O'Callahan
Author-email: fmora@cs.toronto.edu, lukasocallahan@gmail.com
License: UNKNOWN
Platform: UNKNOWN
Classifier: Programming Language :: Python :: 3
Classifier: License :: OSI Approved :: MIT License
Classifier: Operating System :: POSIX :: Linux
Requires-Dist: mongoengine
Requires-Dist: matplotlib
Requires-Dist: numpy
Requires-Dist: progressbar2
Requires-Dist: pymongo
Requires-Dist: psutil
